MANIFEST.in
README.md
pyproject.toml
setup.py
amuse_simplex.egg-info/PKG-INFO
amuse_simplex.egg-info/SOURCES.txt
amuse_simplex.egg-info/dependency_links.txt
amuse_simplex.egg-info/requires.txt
amuse_simplex.egg-info/top_level.txt
src/amuse/community/simplex/Makefile
src/amuse/community/simplex/__init__.py
src/amuse/community/simplex/_version.py
src/amuse/community/simplex/interface.py
src/amuse/community/simplex/data/input/C.Hcool
src/amuse/community/simplex/data/input/C.cool
src/amuse/community/simplex/data/input/Fe.Hcool
src/amuse/community/simplex/data/input/Fe.cool
src/amuse/community/simplex/data/input/H.Hcool
src/amuse/community/simplex/data/input/H.cool
src/amuse/community/simplex/data/input/H2.Hcool
src/amuse/community/simplex/data/input/He.Hcool
src/amuse/community/simplex/data/input/He.cool
src/amuse/community/simplex/data/input/N.Hcool
src/amuse/community/simplex/data/input/N.cool
src/amuse/community/simplex/data/input/Ne.Hcool
src/amuse/community/simplex/data/input/Ne.cool
src/amuse/community/simplex/data/input/O.Hcool
src/amuse/community/simplex/data/input/O.cool
src/amuse/community/simplex/data/input/Si.Hcool
src/amuse/community/simplex/data/input/Si.cool
src/amuse/community/simplex/data/input/vertices_10.txt
src/amuse/community/simplex/data/input/vertices_test.txt
src/amuse/community/simplex/data/input/vertices_test2.txt
src/amuse/community/simplex/data/input/vertices_test3.txt
src/amuse/community/simplex/src/Makefile
src/amuse/community/simplex/src/bin/empty_dir.txt
src/amuse/community/simplex/src/obj/empty_dir.txt
src/amuse/community/simplex/src/plugins/HEALPix/include/alm.h
src/amuse/community/simplex/src/plugins/HEALPix/include/alm_fitsio.h
src/amuse/community/simplex/src/plugins/HEALPix/include/alm_healpix_tools.h
src/amuse/community/simplex/src/plugins/HEALPix/include/alm_map_tools.h
src/amuse/community/simplex/src/plugins/HEALPix/include/alm_powspec_tools.h
src/amuse/community/simplex/src/plugins/HEALPix/include/arr.h
src/amuse/community/simplex/src/plugins/HEALPix/include/cxxutils.h
src/amuse/community/simplex/src/plugins/HEALPix/include/datatypes.h
src/amuse/community/simplex/src/plugins/HEALPix/include/fftpack_support.h
